<keymap version="1" name="Default copy 4" parent="$default">
  <action id="ChangesView.Diff" />
  <action id="CommentByLineComment">
    <keyboard-shortcut first-keystroke="ctrl slash" />
    <keyboard-shortcut first-keystroke="ctrl divide" />
    <keyboard-shortcut first-keystroke="shift ctrl c" />
  </action>
  <action id="CompareTwoFiles" />
  <action id="Console.Execute.Multiline" />
  <action id="CopyPaths" />
  <action id="Diff.ShowDiff" />
  <action id="DirDiffMenu.SynchronizeDiff.All" />
  <action id="EditorDuplicate" />
  <action id="EditorSplitLine" />
  <action id="ExecuteInPyConsoleAction">
    <keyboard-shortcut first-keystroke="shift alt e" />
    <keyboard-shortcut first-keystroke="ctrl enter" />
  </action>
  <action id="FileChooser.GotoDesktop" />
  <action id="RecentFiles" />
  <action id="RunDashboard.CopyConfiguration" />
  <action id="SelectNextOccurrence">
    <keyboard-shortcut first-keystroke="alt j" />
    <keyboard-shortcut first-keystroke="ctrl d" />
  </action>
  <action id="SendEOF" />
  <action id="UnselectPreviousOccurrence">
    <keyboard-shortcut first-keystroke="shift alt j" />
    <keyboard-shortcut first-keystroke="ctrl e" />
  </action>
  <action id="Vcs.ShowMessageHistory">
    <keyboard-shortcut first-keystroke="ctrl m" />
  </action>
  <action id="ViewSource" />
  <action id="XDebugger.CopyWatch" />
  <action id="openAssertEqualsDiff" />
</keymap>